runseq.py
runseq-0.3.0.dist-info/LICENSE
runseq-0.3.0.dist-info/METADATA
runseq-0.3.0.dist-info/WHEEL
runseq-0.3.0.dist-info/entry_points.txt
runseq-0.3.0.dist-info/top_level.txt
runseq-0.3.0.dist-info/RECORD
