Metadata-Version: 2.1
Name: runseq
Version: 0.3.0
Summary: Simple job manager to run jobs sequentially in a Linux machine.
Author-email: Luís Gomes <luismsgomes@gmail.com>
License: GNU GENERAL PUBLIC LICENSE
Project-URL: Homepage, https://github.com/luismsgomes/runseq
Requires-Python: >=3.8
License-File: LICENSE
